[
    {
        "id": 789544041822220288,
        "id_str": "789544041822220288",
        "name": "Ingo Philipp",
        "screen_name": "IngoPhilipp",
        "location": "Vienna, Austria",
        "url": "https://www.linkedin.com/in/ingophilipp/",
        "description": "",
        "protected": false,
        "followers_count": 359,
        "friends_count": 113,
        "listed_count": 3,
        "created_at": "Fri Oct 21 19:09:03 +0000 2016",
        "favourites_count": 689,
        "utc_offset": null,
        "time_zone": null,
        "geo_enabled": false,
        "verified": false,
        "statuses_count": 979,
        "lang": null,
        "contributors_enabled": false,
        "is_translator": false,
        "is_translation_enabled": false,
        "profile_background_color": "000000",
        "profile_background_image_url": "http://abs.twimg.com/images/themes/theme1/bg.png",
        "profile_background_image_url_https": "https://abs.twimg.com/images/themes/theme1/bg.png",
        "profile_background_tile": false,
        "profile_image_url": "http://pbs.twimg.com/profile_images/1122915209704767490/T9gubc1C_normal.png",
        "profile_image_url_https": "https://pbs.twimg.com/profile_images/1122915209704767490/T9gubc1C_normal.png",
        "profile_banner_url": "https://pbs.twimg.com/profile_banners/789544041822220288/1564493909",
        "profile_link_color": "1B95E0",
        "profile_sidebar_border_color": "000000",
        "profile_sidebar_fill_color": "000000",
        "profile_text_color": "000000",
        "profile_use_background_image": false,
        "has_extended_profile": false,
        "default_profile": false,
        "default_profile_image": false,
        "following": false,
        "live_following": false,
        "follow_request_sent": false,
        "notifications": false,
        "muting": false,
        "blocking": false,
        "blocked_by": false,
        "translator_type": "none"
    },
    {
        "id": 709838144737288193,
        "id_str": "709838144737288193",
        "name": "TestSphere",
        "screen_name": "TestSphere",
        "location": "",
        "url": "https://store.ministryoftesting.com/collections/testsphere",
        "description": "The card game that gets testers talking, thinking & learning about their experiences. \nPerfect for workshops, conferences... \nCreated with @MinistryOfTest",
        "protected": false,
        "followers_count": 1641,
        "friends_count": 456,
        "listed_count": 22,
        "created_at": "Tue Mar 15 20:26:16 +0000 2016",
        "favourites_count": 1468,
        "utc_offset": null,
        "time_zone": null,
        "geo_enabled": false,
        "verified": false,
        "statuses_count": 1101,
        "lang": null,
        "contributors_enabled": false,
        "is_translator": false,
        "is_translation_enabled": false,
        "profile_background_color": "000000",
        "profile_background_image_url": "http://abs.twimg.com/images/themes/theme1/bg.png",
        "profile_background_image_url_https": "https://abs.twimg.com/images/themes/theme1/bg.png",
        "profile_background_tile": false,
        "profile_image_url": "http://pbs.twimg.com/profile_images/768428728942727168/qdfQxlTx_normal.jpg",
        "profile_image_url_https": "https://pbs.twimg.com/profile_images/768428728942727168/qdfQxlTx_normal.jpg",
        "profile_banner_url": "https://pbs.twimg.com/profile_banners/709838144737288193/1468770032",
        "profile_link_color": "1B95E0",
        "profile_sidebar_border_color": "000000",
        "profile_sidebar_fill_color": "000000",
        "profile_text_color": "000000",
        "profile_use_background_image": false,
        "has_extended_profile": false,
        "default_profile": false,
        "default_profile_image": false,
        "following": false,
        "live_following": false,
        "follow_request_sent": false,
        "notifications": false,
        "muting": false,
        "blocking": false,
        "blocked_by": false,
        "translator_type": "none"
    },
    {
        "id": 719813135599812608,
        "id_str": "719813135599812608",
        "name": "Dominic Kua",
        "screen_name": "Testing_crafty",
        "location": "Cambridge, England",
        "url": "http://kua.org.uk",
        "description": "A software tester, gardener, cook, father, gamer, general reader and scientist from Manchester, living in the East of England. Python enthusiast he/him",
        "protected": false,
        "followers_count": 832,
        "friends_count": 207,
        "listed_count": 14,
        "created_at": "Tue Apr 12 09:03:19 +0000 2016",
        "favourites_count": 568,
        "utc_offset": null,
        "time_zone": null,
        "geo_enabled": true,
        "verified": false,
        "statuses_count": 993,
        "lang": null,
        "contributors_enabled": false,
        "is_translator": false,
        "is_translation_enabled": false,
        "profile_background_color": "000000",
        "profile_background_image_url": "http://abs.twimg.com/images/themes/theme1/bg.png",
        "profile_background_image_url_https": "https://abs.twimg.com/images/themes/theme1/bg.png",
        "profile_background_tile": false,
        "profile_image_url": "http://pbs.twimg.com/profile_images/856809961250312192/2sIBxANF_normal.jpg",
        "profile_image_url_https": "https://pbs.twimg.com/profile_images/856809961250312192/2sIBxANF_normal.jpg",
        "profile_banner_url": "https://pbs.twimg.com/profile_banners/719813135599812608/1493114419",
        "profile_link_color": "7FDBB6",
        "profile_sidebar_border_color": "000000",
        "profile_sidebar_fill_color": "000000",
        "profile_text_color": "000000",
        "profile_use_background_image": true,
        "has_extended_profile": false,
        "default_profile": false,
        "default_profile_image": false,
        "following": false,
        "live_following": false,
        "follow_request_sent": false,
        "notifications": false,
        "muting": false,
        "blocking": false,
        "blocked_by": false,
        "translator_type": "none"
    },
    {
        "id": 400706716,
        "id_str": "400706716",
        "name": "TMMi Foundation",
        "screen_name": "TMMiFoundation",
        "location": "",
        "url": null,
        "description": "The TMMi Foundation, a non-profit organization, dedicated to improving test processes and practice.",
        "protected": false,
        "followers_count": 771,
        "friends_count": 1534,
        "listed_count": 10,
        "created_at": "Sat Oct 29 13:06:30 +0000 2011",
        "favourites_count": 294,
        "utc_offset": null,
        "time_zone": null,
        "geo_enabled": true,
        "verified": false,
        "statuses_count": 394,
        "lang": null,
        "contributors_enabled": false,
        "is_translator": false,
        "is_translation_enabled": false,
        "profile_background_color": "C0DEED",
        "profile_background_image_url": "http://abs.twimg.com/images/themes/theme1/bg.png",
        "profile_background_image_url_https": "https://abs.twimg.com/images/themes/theme1/bg.png",
        "profile_background_tile": false,
        "profile_image_url": "http://pbs.twimg.com/profile_images/1121760885100482560/vU0JNIZl_normal.jpg",
        "profile_image_url_https": "https://pbs.twimg.com/profile_images/1121760885100482560/vU0JNIZl_normal.jpg",
        "profile_banner_url": "https://pbs.twimg.com/profile_banners/400706716/1556283612",
        "profile_link_color": "1DA1F2",
        "profile_sidebar_border_color": "C0DEED",
        "profile_sidebar_fill_color": "DDEEF6",
        "profile_text_color": "333333",
        "profile_use_background_image": true,
        "has_extended_profile": false,
        "default_profile": true,
        "default_profile_image": false,
        "following": false,
        "live_following": false,
        "follow_request_sent": false,
        "notifications": false,
        "muting": false,
        "blocking": false,
        "blocked_by": false,
        "translator_type": "none"
    },
    {
        "id": 567703294,
        "id_str": "567703294",
        "name": "Erik van Veenendaal",
        "screen_name": "ErikvVeenendaal",
        "location": "Kralendijk, Bonaire",
        "url": "http://www.erikvanveenendaal.nl",
        "description": "software testing expert, independent test and quality consultant / trainer and table tennis coach. Husband, three great kids & bruce springsteen fan.",
        "protected": false,
        "followers_count": 716,
        "friends_count": 102,
        "listed_count": 30,
        "created_at": "Tue May 01 00:41:51 +0000 2012",
        "favourites_count": 466,
        "utc_offset": null,
        "time_zone": null,
        "geo_enabled": false,
        "verified": false,
        "statuses_count": 1806,
        "lang": null,
        "contributors_enabled": false,
        "is_translator": false,
        "is_translation_enabled": false,
        "profile_background_color": "C0DEED",
        "profile_background_image_url": "http://abs.twimg.com/images/themes/theme1/bg.png",
        "profile_background_image_url_https": "https://abs.twimg.com/images/themes/theme1/bg.png",
        "profile_background_tile": false,
        "profile_image_url": "http://pbs.twimg.com/profile_images/789532307002630145/IP45Rxc4_normal.jpg",
        "profile_image_url_https": "https://pbs.twimg.com/profile_images/789532307002630145/IP45Rxc4_normal.jpg",
        "profile_banner_url": "https://pbs.twimg.com/profile_banners/567703294/1510082432",
        "profile_link_color": "1DA1F2",
        "profile_sidebar_border_color": "C0DEED",
        "profile_sidebar_fill_color": "DDEEF6",
        "profile_text_color": "333333",
        "profile_use_background_image": true,
        "has_extended_profile": false,
        "default_profile": true,
        "default_profile_image": false,
        "following": false,
        "live_following": false,
        "follow_request_sent": false,
        "notifications": false,
        "muting": false,
        "blocking": false,
        "blocked_by": false,
        "translator_type": "none"
    },
    {
        "id": 725662113486753792,
        "id_str": "725662113486753792",
        "name": "Lina Zubyte",
        "screen_name": "buggylina",
        "location": "Berlin, Germany",
        "url": "https://qualitybits.tech",
        "description": "I care about all things quality, human connection, social change, feminism, and diversity & inclusion. My favorite emoji is sparkles ✨ she/her",
        "protected": false,
        "followers_count": 860,
        "friends_count": 390,
        "listed_count": 19,
        "created_at": "Thu Apr 28 12:25:04 +0000 2016",
        "favourites_count": 547,
        "utc_offset": null,
        "time_zone": null,
        "geo_enabled": false,
        "verified": false,
        "statuses_count": 933,
        "lang": null,
        "contributors_enabled": false,
        "is_translator": false,
        "is_translation_enabled": false,
        "profile_background_color": "F5F8FA",
        "profile_background_image_url": null,
        "profile_background_image_url_https": null,
        "profile_background_tile": false,
        "profile_image_url": "http://pbs.twimg.com/profile_images/1216475046367186945/AE5gHxhU_normal.jpg",
        "profile_image_url_https": "https://pbs.twimg.com/profile_images/1216475046367186945/AE5gHxhU_normal.jpg",
        "profile_banner_url": "https://pbs.twimg.com/profile_banners/725662113486753792/1588002887",
        "profile_link_color": "1DA1F2",
        "profile_sidebar_border_color": "C0DEED",
        "profile_sidebar_fill_color": "DDEEF6",
        "profile_text_color": "333333",
        "profile_use_background_image": true,
        "has_extended_profile": false,
        "default_profile": true,
        "default_profile_image": false,
        "following": false,
        "live_following": false,
        "follow_request_sent": false,
        "notifications": false,
        "muting": false,
        "blocking": false,
        "blocked_by": false,
        "translator_type": "none"
    },
    {
        "id": 15171615,
        "id_str": "15171615",
        "name": "lisacrispin",
        "screen_name": "lisacrispin",
        "location": "Charlotte, VT!",
        "url": "https://lisacrispin.com",
        "description": "Now available, Amazon & LeanPub: _Agile Testing Condensed_! See https://t.co/KDbFTkGIu8,  https://t.co/DXOlUdYqKw, She/her. Quality owner, @OutSystems R&D, #o11y-bound!",
        "protected": false,
        "followers_count": 19778,
        "friends_count": 5882,
        "listed_count": 1181,
        "created_at": "Thu Jun 19 18:06:04 +0000 2008",
        "favourites_count": 32497,
        "utc_offset": null,
        "time_zone": null,
        "geo_enabled": false,
        "verified": false,
        "statuses_count": 137228,
        "lang": null,
        "contributors_enabled": false,
        "is_translator": false,
        "is_translation_enabled": false,
        "profile_background_color": "C0DEED",
        "profile_background_image_url": "http://abs.twimg.com/images/themes/theme1/bg.png",
        "profile_background_image_url_https": "https://abs.twimg.com/images/themes/theme1/bg.png",
        "profile_background_tile": false,
        "profile_image_url": "http://pbs.twimg.com/profile_images/1317871769252933634/UkljTlTL_normal.jpg",
        "profile_image_url_https": "https://pbs.twimg.com/profile_images/1317871769252933634/UkljTlTL_normal.jpg",
        "profile_banner_url": "https://pbs.twimg.com/profile_banners/15171615/1591789297",
        "profile_link_color": "1DA1F2",
        "profile_sidebar_border_color": "C0DEED",
        "profile_sidebar_fill_color": "DDEEF6",
        "profile_text_color": "333333",
        "profile_use_background_image": true,
        "has_extended_profile": false,
        "default_profile": true,
        "default_profile_image": false,
        "following": false,
        "live_following": false,
        "follow_request_sent": false,
        "notifications": false,
        "muting": false,
        "blocking": false,
        "blocked_by": false,
        "translator_type": "none"
    },
    {
        "id": 143488289,
        "id_str": "143488289",
        "name": "Maaret Pyhäjärvi",
        "screen_name": "maaretp",
        "location": "Finland",
        "url": "http://maaretp.com",
        "description": "Feedback fairy with a day-job at Vaisala as Principal Test Engineer. Tester, (Polyglot) Programmer, Speaker, Author, Conference Designer. She/Her. maaret@iki.fi",
        "protected": false,
        "followers_count": 6239,
        "friends_count": 1048,
        "listed_count": 263,
        "created_at": "Thu May 13 16:12:26 +0000 2010",
        "favourites_count": 6139,
        "utc_offset": null,
        "time_zone": null,
        "geo_enabled": true,
        "verified": false,
        "statuses_count": 26710,
        "lang": null,
        "contributors_enabled": false,
        "is_translator": false,
        "is_translation_enabled": false,
        "profile_background_color": "FF6699",
        "profile_background_image_url": "http://abs.twimg.com/images/themes/theme10/bg.gif",
        "profile_background_image_url_https": "https://abs.twimg.com/images/themes/theme10/bg.gif",
        "profile_background_tile": true,
        "profile_image_url": "http://pbs.twimg.com/profile_images/1297199340562403328/I-ap24VC_normal.jpg",
        "profile_image_url_https": "https://pbs.twimg.com/profile_images/1297199340562403328/I-ap24VC_normal.jpg",
        "profile_banner_url": "https://pbs.twimg.com/profile_banners/143488289/1556785145",
        "profile_link_color": "1B95E0",
        "profile_sidebar_border_color": "C0DEED",
        "profile_sidebar_fill_color": "DDEEF6",
        "profile_text_color": "333333",
        "profile_use_background_image": true,
        "has_extended_profile": false,
        "default_profile": false,
        "default_profile_image": false,
        "following": false,
        "live_following": false,
        "follow_request_sent": false,
        "notifications": false,
        "muting": false,
        "blocking": false,
        "blocked_by": false,
        "translator_type": "none"
    },
    {
        "id": 212568672,
        "id_str": "212568672",
        "name": "Alex Schladebeck",
        "screen_name": "alex_schl",
        "location": "",
        "url": "http://www.schladebeck.de",
        "description": "Agile tester. Consultant. International keynote speaker. Linguist, musician, extrovert. Communicator. Sport & adrenaline junkie.\n\nCEO at BREDEX GmbH.\nShe/her.",
        "protected": false,
        "followers_count": 4129,
        "friends_count": 1255,
        "listed_count": 158,
        "created_at": "Sat Nov 06 13:01:15 +0000 2010",
        "favourites_count": 6908,
        "utc_offset": null,
        "time_zone": null,
        "geo_enabled": false,
        "verified": false,
        "statuses_count": 12374,
        "lang": null,
        "contributors_enabled": false,
        "is_translator": false,
        "is_translation_enabled": false,
        "profile_background_color": "000000",
        "profile_background_image_url": "http://abs.twimg.com/images/themes/theme3/bg.gif",
        "profile_background_image_url_https": "https://abs.twimg.com/images/themes/theme3/bg.gif",
        "profile_background_tile": false,
        "profile_image_url": "http://pbs.twimg.com/profile_images/1196107201313726464/2lF98R0u_normal.jpg",
        "profile_image_url_https": "https://pbs.twimg.com/profile_images/1196107201313726464/2lF98R0u_normal.jpg",
        "profile_banner_url": "https://pbs.twimg.com/profile_banners/212568672/1558964025",
        "profile_link_color": "5C005C",
        "profile_sidebar_border_color": "000000",
        "profile_sidebar_fill_color": "000000",
        "profile_text_color": "000000",
        "profile_use_background_image": false,
        "has_extended_profile": true,
        "default_profile": false,
        "default_profile_image": false,
        "following": false,
        "live_following": false,
        "follow_request_sent": false,
        "notifications": false,
        "muting": false,
        "blocking": false,
        "blocked_by": false,
        "translator_type": "none"
    },
    {
        "id": 58644658,
        "id_str": "58644658",
        "name": "Fiona Charles",
        "screen_name": "FionaCCharles",
        "location": "Kingston, Ontario, Canada",
        "url": "http://www.quality-intelligence.com",
        "description": "Software test consultant, teacher, writer, speaker, iconoclast. I lead workshops \"beyond process\", coach, renovate & rescue testing of any scale.",
        "protected": false,
        "followers_count": 5193,
        "friends_count": 575,
        "listed_count": 182,
        "created_at": "Tue Jul 21 00:32:04 +0000 2009",
        "favourites_count": 42996,
        "utc_offset": null,
        "time_zone": null,
        "geo_enabled": true,
        "verified": false,
        "statuses_count": 8181,
        "lang": null,
        "contributors_enabled": false,
        "is_translator": false,
        "is_translation_enabled": false,
        "profile_background_color": "C0DEED",
        "profile_background_image_url": "http://abs.twimg.com/images/themes/theme1/bg.png",
        "profile_background_image_url_https": "https://abs.twimg.com/images/themes/theme1/bg.png",
        "profile_background_tile": false,
        "profile_image_url": "http://pbs.twimg.com/profile_images/1285992577532080129/I4bw6_7d_normal.jpg",
        "profile_image_url_https": "https://pbs.twimg.com/profile_images/1285992577532080129/I4bw6_7d_normal.jpg",
        "profile_link_color": "0084B4",
        "profile_sidebar_border_color": "C0DEED",
        "profile_sidebar_fill_color": "DDEEF6",
        "profile_text_color": "333333",
        "profile_use_background_image": true,
        "has_extended_profile": false,
        "default_profile": false,
        "default_profile_image": false,
        "following": false,
        "live_following": false,
        "follow_request_sent": false,
        "notifications": false,
        "muting": false,
        "blocking": false,
        "blocked_by": false,
        "translator_type": "none"
    }
]