[
    {
        "id": 18198841,
        "id_str": "18198841",
        "name": "Ryan Scott Graham",
        "screen_name": "RyanScottGraham",
        "location": "Emotional Babylon",
        "url": null,
        "description": "@State_Champs / @SpeakLowMusic",
        "protected": false,
        "followers_count": 58449,
        "friends_count": 1049,
        "listed_count": 188,
        "created_at": "Wed Dec 17 20:33:10 +0000 2008",
        "favourites_count": 76274,
        "utc_offset": null,
        "time_zone": null,
        "geo_enabled": true,
        "verified": true,
        "statuses_count": 85389,
        "lang": null,
        "contributors_enabled": false,
        "is_translator": false,
        "is_translation_enabled": false,
        "profile_background_color": "C0DEED",
        "profile_background_image_url": "http://abs.twimg.com/images/themes/theme1/bg.png",
        "profile_background_image_url_https": "https://abs.twimg.com/images/themes/theme1/bg.png",
        "profile_background_tile": false,
        "profile_image_url": "http://pbs.twimg.com/profile_images/1195147699949113344/vfO4ohpY_normal.jpg",
        "profile_image_url_https": "https://pbs.twimg.com/profile_images/1195147699949113344/vfO4ohpY_normal.jpg",
        "profile_banner_url": "https://pbs.twimg.com/profile_banners/18198841/1587668658",
        "profile_link_color": "0084B4",
        "profile_sidebar_border_color": "FFFFFF",
        "profile_sidebar_fill_color": "DDEEF6",
        "profile_text_color": "333333",
        "profile_use_background_image": true,
        "has_extended_profile": true,
        "default_profile": false,
        "default_profile_image": false,
        "following": false,
        "live_following": false,
        "follow_request_sent": false,
        "notifications": false,
        "muting": false,
        "blocking": false,
        "blocked_by": false,
        "translator_type": "none"
    },
    {
        "id": 1038929823257702400,
        "id_str": "1038929823257702400",
        "name": "eartha is focusing on er countdown + being better",
        "screen_name": "ukleghoul",
        "location": "Colonized Lenapehoking",
        "url": null,
        "description": "eartha mae//she/her/e/er/dr//🏴postdoc studying neural systems, hormonal plasticity, + social brains//\"evolutionarily...a big mistake\"//demi+bi//personal acct",
        "protected": false,
        "followers_count": 3544,
        "friends_count": 748,
        "listed_count": 12,
        "created_at": "Sun Sep 09 23:19:07 +0000 2018",
        "favourites_count": 33284,
        "utc_offset": null,
        "time_zone": null,
        "geo_enabled": false,
        "verified": false,
        "statuses_count": 12630,
        "lang": null,
        "contributors_enabled": false,
        "is_translator": false,
        "is_translation_enabled": false,
        "profile_background_color": "000000",
        "profile_background_image_url": "http://abs.twimg.com/images/themes/theme1/bg.png",
        "profile_background_image_url_https": "https://abs.twimg.com/images/themes/theme1/bg.png",
        "profile_background_tile": false,
        "profile_image_url": "http://pbs.twimg.com/profile_images/1308265394881417216/FSM6z7Kt_normal.jpg",
        "profile_image_url_https": "https://pbs.twimg.com/profile_images/1308265394881417216/FSM6z7Kt_normal.jpg",
        "profile_banner_url": "https://pbs.twimg.com/profile_banners/1038929823257702400/1588098030",
        "profile_link_color": "ECBAB9",
        "profile_sidebar_border_color": "000000",
        "profile_sidebar_fill_color": "000000",
        "profile_text_color": "000000",
        "profile_use_background_image": false,
        "has_extended_profile": false,
        "default_profile": false,
        "default_profile_image": false,
        "following": false,
        "live_following": false,
        "follow_request_sent": false,
        "notifications": false,
        "muting": false,
        "blocking": false,
        "blocked_by": false,
        "translator_type": "none"
    },
    {
        "id": 825569108649340928,
        "id_str": "825569108649340928",
        "name": "Sarah Olson Michel",
        "screen_name": "ReadMoreScience",
        "location": "Oregon",
        "url": "https://readmorescience.com",
        "description": "Science book reviews and more. Twitter account is on hiatus but DM's are monitored | she/they 📚🔬",
        "protected": false,
        "followers_count": 16036,
        "friends_count": 4139,
        "listed_count": 127,
        "created_at": "Sun Jan 29 04:59:48 +0000 2017",
        "favourites_count": 99613,
        "utc_offset": null,
        "time_zone": null,
        "geo_enabled": true,
        "verified": false,
        "statuses_count": 30114,
        "lang": null,
        "contributors_enabled": false,
        "is_translator": false,
        "is_translation_enabled": false,
        "profile_background_color": "000000",
        "profile_background_image_url": "http://abs.twimg.com/images/themes/theme1/bg.png",
        "profile_background_image_url_https": "https://abs.twimg.com/images/themes/theme1/bg.png",
        "profile_background_tile": false,
        "profile_image_url": "http://pbs.twimg.com/profile_images/1322423095651565568/-j99msBY_normal.jpg",
        "profile_image_url_https": "https://pbs.twimg.com/profile_images/1322423095651565568/-j99msBY_normal.jpg",
        "profile_banner_url": "https://pbs.twimg.com/profile_banners/825569108649340928/1604118316",
        "profile_link_color": "1B95E0",
        "profile_sidebar_border_color": "000000",
        "profile_sidebar_fill_color": "000000",
        "profile_text_color": "000000",
        "profile_use_background_image": false,
        "has_extended_profile": true,
        "default_profile": false,
        "default_profile_image": false,
        "following": false,
        "live_following": false,
        "follow_request_sent": false,
        "notifications": false,
        "muting": false,
        "blocking": false,
        "blocked_by": false,
        "translator_type": "none"
    },
    {
        "id": 337680171,
        "id_str": "337680171",
        "name": "Faye Vassel, PhD 👩🏾‍🔬🧬⇌👩🏾‍💻📚 #BlackinSTEM",
        "screen_name": "fayevass",
        "location": "Washington, DC ",
        "url": null,
        "description": "Cancer Biology PhD @MITBiology |Science Policy Fellow @AAAS_STPF & @NSF|STEM ED Equity Research Postdoc @Georgetown|Bronx Native @NYC|Views My Own",
        "protected": false,
        "followers_count": 235,
        "friends_count": 1368,
        "listed_count": 2,
        "created_at": "Mon Jul 18 12:18:59 +0000 2011",
        "favourites_count": 7427,
        "utc_offset": null,
        "time_zone": null,
        "geo_enabled": true,
        "verified": false,
        "statuses_count": 502,
        "lang": null,
        "contributors_enabled": false,
        "is_translator": false,
        "is_translation_enabled": false,
        "profile_background_color": "C0DEED",
        "profile_background_image_url": "http://abs.twimg.com/images/themes/theme1/bg.png",
        "profile_background_image_url_https": "https://abs.twimg.com/images/themes/theme1/bg.png",
        "profile_background_tile": true,
        "profile_image_url": "http://pbs.twimg.com/profile_images/1169057959575470080/RE44nlUC_normal.jpg",
        "profile_image_url_https": "https://pbs.twimg.com/profile_images/1169057959575470080/RE44nlUC_normal.jpg",
        "profile_link_color": "F5ABB5",
        "profile_sidebar_border_color": "C0DEED",
        "profile_sidebar_fill_color": "DDEEF6",
        "profile_text_color": "333333",
        "profile_use_background_image": true,
        "has_extended_profile": false,
        "default_profile": false,
        "default_profile_image": false,
        "following": false,
        "live_following": false,
        "follow_request_sent": false,
        "notifications": false,
        "muting": false,
        "blocking": false,
        "blocked_by": false,
        "translator_type": "none"
    },
    {
        "id": 89093206,
        "id_str": "89093206",
        "name": "G.Denise",
        "screen_name": "TheGDenise",
        "location": "Made in NYC, Tailored In Truth",
        "url": "http://instagram.com/gdenisewrites",
        "description": "A perpetually-curious Black realist and a dyke who writes prose when not exhausted by capitalism. Godless, skeptical. Radically rude woman. Hater of stupidity.",
        "protected": false,
        "followers_count": 11940,
        "friends_count": 1695,
        "listed_count": 293,
        "created_at": "Wed Nov 11 03:09:03 +0000 2009",
        "favourites_count": 28324,
        "utc_offset": null,
        "time_zone": null,
        "geo_enabled": true,
        "verified": false,
        "statuses_count": 2117,
        "lang": null,
        "contributors_enabled": false,
        "is_translator": false,
        "is_translation_enabled": false,
        "profile_background_color": "352726",
        "profile_background_image_url": "http://abs.twimg.com/images/themes/theme5/bg.gif",
        "profile_background_image_url_https": "https://abs.twimg.com/images/themes/theme5/bg.gif",
        "profile_background_tile": true,
        "profile_image_url": "http://pbs.twimg.com/profile_images/1315478580881764352/d1ZD_6ZZ_normal.jpg",
        "profile_image_url_https": "https://pbs.twimg.com/profile_images/1315478580881764352/d1ZD_6ZZ_normal.jpg",
        "profile_banner_url": "https://pbs.twimg.com/profile_banners/89093206/1604799977",
        "profile_link_color": "19CF86",
        "profile_sidebar_border_color": "829D5E",
        "profile_sidebar_fill_color": "99CC33",
        "profile_text_color": "3E4415",
        "profile_use_background_image": false,
        "has_extended_profile": true,
        "default_profile": false,
        "default_profile_image": false,
        "following": false,
        "live_following": false,
        "follow_request_sent": false,
        "notifications": false,
        "muting": false,
        "blocking": false,
        "blocked_by": false,
        "translator_type": "none"
    },
    {
        "id": 110326494,
        "id_str": "110326494",
        "name": "Brent Newsome Purdy, Non-Aggressive White Man",
        "screen_name": "BreeNewsome",
        "location": "North Carolina, USA",
        "url": "http://whentheyseeusvote.com",
        "description": "artist - free black woman - scaled 30ft flagpole & removed sc confederate flag in protest on june 27, 2015 - Isaiah 54:17",
        "protected": false,
        "followers_count": 400098,
        "friends_count": 2008,
        "listed_count": 2985,
        "created_at": "Mon Feb 01 04:33:43 +0000 2010",
        "favourites_count": 30432,
        "utc_offset": null,
        "time_zone": null,
        "geo_enabled": false,
        "verified": true,
        "statuses_count": 24944,
        "lang": null,
        "contributors_enabled": false,
        "is_translator": false,
        "is_translation_enabled": false,
        "profile_background_color": "000000",
        "profile_background_image_url": "http://abs.twimg.com/images/themes/theme6/bg.gif",
        "profile_background_image_url_https": "https://abs.twimg.com/images/themes/theme6/bg.gif",
        "profile_background_tile": false,
        "profile_image_url": "http://pbs.twimg.com/profile_images/1326547571804790784/AdMomJFO_normal.jpg",
        "profile_image_url_https": "https://pbs.twimg.com/profile_images/1326547571804790784/AdMomJFO_normal.jpg",
        "profile_banner_url": "https://pbs.twimg.com/profile_banners/110326494/1435808027",
        "profile_link_color": "FF3300",
        "profile_sidebar_border_color": "FFFFFF",
        "profile_sidebar_fill_color": "A0C5C7",
        "profile_text_color": "333333",
        "profile_use_background_image": true,
        "has_extended_profile": true,
        "default_profile": false,
        "default_profile_image": false,
        "following": false,
        "live_following": false,
        "follow_request_sent": false,
        "notifications": false,
        "muting": false,
        "blocking": false,
        "blocked_by": false,
        "translator_type": "none"
    },
    {
        "id": 226716243,
        "id_str": "226716243",
        "name": "hans",
        "screen_name": "voteforhani",
        "location": "london",
        "url": "https://m.youtube.com/c/VoteForHani?sub_confirmation=1",
        "description": "dr 👩🏾‍⚕️ | skincare + science | ig: voteforhani ⁷. skincare features in The Times, Byrdie and Vice",
        "protected": false,
        "followers_count": 22179,
        "friends_count": 763,
        "listed_count": 27,
        "created_at": "Tue Dec 14 22:04:43 +0000 2010",
        "favourites_count": 31770,
        "utc_offset": null,
        "time_zone": null,
        "geo_enabled": true,
        "verified": false,
        "statuses_count": 17172,
        "lang": null,
        "contributors_enabled": false,
        "is_translator": false,
        "is_translation_enabled": false,
        "profile_background_color": "000000",
        "profile_background_image_url": "http://abs.twimg.com/images/themes/theme1/bg.png",
        "profile_background_image_url_https": "https://abs.twimg.com/images/themes/theme1/bg.png",
        "profile_background_tile": false,
        "profile_image_url": "http://pbs.twimg.com/profile_images/1294410305666273280/nkrkl3EO_normal.jpg",
        "profile_image_url_https": "https://pbs.twimg.com/profile_images/1294410305666273280/nkrkl3EO_normal.jpg",
        "profile_banner_url": "https://pbs.twimg.com/profile_banners/226716243/1604615864",
        "profile_link_color": "9266CC",
        "profile_sidebar_border_color": "000000",
        "profile_sidebar_fill_color": "000000",
        "profile_text_color": "000000",
        "profile_use_background_image": false,
        "has_extended_profile": true,
        "default_profile": false,
        "default_profile_image": false,
        "following": false,
        "live_following": false,
        "follow_request_sent": false,
        "notifications": false,
        "muting": false,
        "blocking": false,
        "blocked_by": false,
        "translator_type": "none"
    },
    {
        "id": 1250977648941162496,
        "id_str": "1250977648941162496",
        "name": "Nzuekoh Nchinda, MD",
        "screen_name": "nzuekoh",
        "location": "Seattle, WA",
        "url": null,
        "description": "PGY1 @UWSurgery who cares about equity, ethics & QI/outcomes research. An alum of @UChiPritzker + @Harvard, runner & art enthusiast.",
        "protected": false,
        "followers_count": 727,
        "friends_count": 543,
        "listed_count": 6,
        "created_at": "Fri Apr 17 02:41:57 +0000 2020",
        "favourites_count": 472,
        "utc_offset": null,
        "time_zone": null,
        "geo_enabled": false,
        "verified": false,
        "statuses_count": 50,
        "lang": null,
        "contributors_enabled": false,
        "is_translator": false,
        "is_translation_enabled": false,
        "profile_background_color": "F5F8FA",
        "profile_background_image_url": null,
        "profile_background_image_url_https": null,
        "profile_background_tile": false,
        "profile_image_url": "http://pbs.twimg.com/profile_images/1250977896233144320/9L8_3rLq_normal.jpg",
        "profile_image_url_https": "https://pbs.twimg.com/profile_images/1250977896233144320/9L8_3rLq_normal.jpg",
        "profile_banner_url": "https://pbs.twimg.com/profile_banners/1250977648941162496/1587093563",
        "profile_link_color": "1DA1F2",
        "profile_sidebar_border_color": "C0DEED",
        "profile_sidebar_fill_color": "DDEEF6",
        "profile_text_color": "333333",
        "profile_use_background_image": true,
        "has_extended_profile": true,
        "default_profile": true,
        "default_profile_image": false,
        "following": false,
        "live_following": false,
        "follow_request_sent": false,
        "notifications": false,
        "muting": false,
        "blocking": false,
        "blocked_by": false,
        "translator_type": "none"
    },
    {
        "id": 468479245,
        "id_str": "468479245",
        "name": "Bettina Love",
        "screen_name": "BLoveSoulPower",
        "location": "Atlanta, GA",
        "url": "http://www.bettinalove.com",
        "description": "Professor |Co-founder of ATN | Author of We Want to Do More Than Survive: Abolitionist Teaching https://goo.gl/4hJUaZ | Political and personal views are my own.",
        "protected": false,
        "followers_count": 31488,
        "friends_count": 1890,
        "listed_count": 210,
        "created_at": "Thu Jan 19 15:50:34 +0000 2012",
        "favourites_count": 28804,
        "utc_offset": null,
        "time_zone": null,
        "geo_enabled": true,
        "verified": false,
        "statuses_count": 6695,
        "lang": null,
        "contributors_enabled": false,
        "is_translator": false,
        "is_translation_enabled": false,
        "profile_background_color": "C0DEED",
        "profile_background_image_url": "http://abs.twimg.com/images/themes/theme1/bg.png",
        "profile_background_image_url_https": "https://abs.twimg.com/images/themes/theme1/bg.png",
        "profile_background_tile": false,
        "profile_image_url": "http://pbs.twimg.com/profile_images/1030278476169965568/syw13rqr_normal.jpg",
        "profile_image_url_https": "https://pbs.twimg.com/profile_images/1030278476169965568/syw13rqr_normal.jpg",
        "profile_banner_url": "https://pbs.twimg.com/profile_banners/468479245/1534472506",
        "profile_link_color": "0084B4",
        "profile_sidebar_border_color": "C0DEED",
        "profile_sidebar_fill_color": "DDEEF6",
        "profile_text_color": "333333",
        "profile_use_background_image": true,
        "has_extended_profile": false,
        "default_profile": false,
        "default_profile_image": false,
        "following": false,
        "live_following": false,
        "follow_request_sent": false,
        "notifications": false,
        "muting": false,
        "blocking": false,
        "blocked_by": false,
        "translator_type": "none"
    },
    {
        "id": 821906583613505537,
        "id_str": "821906583613505537",
        "name": "Dr. Kaitlin Gallagher",
        "screen_name": "kait_a_gallaghr",
        "location": "",
        "url": "https://parasiticevolution.weebly.com/",
        "description": "Assistant Professor. Parasitologist. Invertebrate Zoologist. Evolutionary Biologist. Runner. Cat mom. Opinions my own.\nShe/Her/Hers.",
        "protected": false,
        "followers_count": 665,
        "friends_count": 800,
        "listed_count": 7,
        "created_at": "Thu Jan 19 02:26:14 +0000 2017",
        "favourites_count": 8426,
        "utc_offset": null,
        "time_zone": null,
        "geo_enabled": false,
        "verified": false,
        "statuses_count": 2961,
        "lang": null,
        "contributors_enabled": false,
        "is_translator": false,
        "is_translation_enabled": false,
        "profile_background_color": "000000",
        "profile_background_image_url": "http://abs.twimg.com/images/themes/theme1/bg.png",
        "profile_background_image_url_https": "https://abs.twimg.com/images/themes/theme1/bg.png",
        "profile_background_tile": false,
        "profile_image_url": "http://pbs.twimg.com/profile_images/1175191136530419712/VMA4eobL_normal.jpg",
        "profile_image_url_https": "https://pbs.twimg.com/profile_images/1175191136530419712/VMA4eobL_normal.jpg",
        "profile_banner_url": "https://pbs.twimg.com/profile_banners/821906583613505537/1484794499",
        "profile_link_color": "1B95E0",
        "profile_sidebar_border_color": "000000",
        "profile_sidebar_fill_color": "000000",
        "profile_text_color": "000000",
        "profile_use_background_image": false,
        "has_extended_profile": true,
        "default_profile": false,
        "default_profile_image": false,
        "following": false,
        "live_following": false,
        "follow_request_sent": false,
        "notifications": false,
        "muting": false,
        "blocking": false,
        "blocked_by": false,
        "translator_type": "none"
    }
]